oidc/__init__.py
oidc/constants.py
oidc/provider.py
oidc/views.py
oidc/templates/oidc/configure.html
sentry_auth_oidc_cxg-3.0.3.dist-info/LICENSE
sentry_auth_oidc_cxg-3.0.3.dist-info/METADATA
sentry_auth_oidc_cxg-3.0.3.dist-info/WHEEL
sentry_auth_oidc_cxg-3.0.3.dist-info/entry_points.txt
sentry_auth_oidc_cxg-3.0.3.dist-info/top_level.txt
sentry_auth_oidc_cxg-3.0.3.dist-info/RECORD
