Metadata-Version: 2.1
Name: sentry-auth-oidc-cxg
Version: 3.0.3
Summary: OpenID Connect authentication provider for Sentry
Home-page: https://www.getsentry.com
Author: cxg
Author-email: gtcxg@hotmail.com
License: Apache 2.0
Platform: UNKNOWN
Classifier: Intended Audience :: Developers
Classifier: Intended Audience :: System Administrators
Classifier: Operating System :: OS Independent
Classifier: Topic :: Software Development
Requires-Dist: requests (<3.0.0)
Provides-Extra: tests
Requires-Dist: flake8 (<3.6.0,>=3.5.0) ; extra == 'tests'
